{
    "apiVersion": "v1",
    "items": [
        {
            "apiVersion": "v1",
            "kind": "Pod",
            "metadata": {
                "annotations": {
                    "kubernetes.io/limit-ranger": "LimitRanger plugin set: cpu request for container parsec-blackscholes"
                },
                "creationTimestamp": "2024-05-02T15:05:26Z",
                "generateName": "parsec-blackscholes-",
                "labels": {
                    "batch.kubernetes.io/controller-uid": "a185234b-de77-47e7-9190-2eb48d7dcb45",
                    "batch.kubernetes.io/job-name": "parsec-blackscholes",
                    "controller-uid": "a185234b-de77-47e7-9190-2eb48d7dcb45",
                    "job-name": "parsec-blackscholes"
                },
                "name": "parsec-blackscholes-7db7m",
                "namespace": "default",
                "ownerReferences": [
                    {
                        "apiVersion": "batch/v1",
                        "blockOwnerDeletion": true,
                        "controller": true,
                        "kind": "Job",
                        "name": "parsec-blackscholes",
                        "uid": "a185234b-de77-47e7-9190-2eb48d7dcb45"
                    }
                ],
                "resourceVersion": "10112",
                "uid": "f8c0b18d-a53e-4359-93d0-2bcc2bcaa582"
            },
            "spec": {
                "containers": [
                    {
                        "args": [
                            "-c",
                            "taskset -c 1 ./run -a run -S parsec -p blackscholes -i native -n 1"
                        ],
                        "command": [
                            "/bin/sh"
                        ],
                        "image": "anakli/cca:parsec_blackscholes",
                        "imagePullPolicy": "Always",
                        "name": "parsec-blackscholes",
                        "resources": {
                            "requests": {
                                "cpu": "100m"
                            }
                        },
                        "terminationMessagePath": "/dev/termination-log",
                        "terminationMessagePolicy": "File",
                        "volumeMounts": [
                            {
                                "mountPath": "/var/run/secrets/kubernetes.io/serviceaccount",
                                "name": "kube-api-access-9nnpv",
                                "readOnly": true
                            }
                        ]
                    }
                ],
                "dnsPolicy": "ClusterFirst",
                "enableServiceLinks": true,
                "nodeName": "node-a-2core-sljx",
                "nodeSelector": {
                    "cca-project-nodetype": "node-a-2core"
                },
                "preemptionPolicy": "PreemptLowerPriority",
                "priority": 0,
                "restartPolicy": "Never",
                "schedulerName": "default-scheduler",
                "securityContext": {},
                "serviceAccount": "default",
                "serviceAccountName": "default",
                "terminationGracePeriodSeconds": 30,
                "tolerations": [
                    {
                        "effect": "NoExecute",
                        "key": "node.kubernetes.io/not-ready",
                        "operator": "Exists",
                        "tolerationSeconds": 300
                    },
                    {
                        "effect": "NoExecute",
                        "key": "node.kubernetes.io/unreachable",
                        "operator": "Exists",
                        "tolerationSeconds": 300
                    }
                ],
                "volumes": [
                    {
                        "name": "kube-api-access-9nnpv",
                        "projected": {
                            "defaultMode": 420,
                            "sources": [
                                {
                                    "serviceAccountToken": {
                                        "expirationSeconds": 3607,
                                        "path": "token"
                                    }
                                },
                                {
                                    "configMap": {
                                        "items": [
                                            {
                                                "key": "ca.crt",
                                                "path": "ca.crt"
                                            }
                                        ],
                                        "name": "kube-root-ca.crt"
                                    }
                                },
                                {
                                    "downwardAPI": {
                                        "items": [
                                            {
                                                "fieldRef": {
                                                    "apiVersion": "v1",
                                                    "fieldPath": "metadata.namespace"
                                                },
                                                "path": "namespace"
                                            }
                                        ]
                                    }
                                }
                            ]
                        }
                    }
                ]
            },
            "status": {
                "conditions": [
                    {
                        "lastProbeTime": null,
                        "lastTransitionTime": "2024-05-02T15:05:26Z",
                        "reason": "PodCompleted",
                        "status": "True",
                        "type": "Initialized"
                    },
                    {
                        "lastProbeTime": null,
                        "lastTransitionTime": "2024-05-02T15:07:24Z",
                        "reason": "PodCompleted",
                        "status": "False",
                        "type": "Ready"
                    },
                    {
                        "lastProbeTime": null,
                        "lastTransitionTime": "2024-05-02T15:07:24Z",
                        "reason": "PodCompleted",
                        "status": "False",
                        "type": "ContainersReady"
                    },
                    {
                        "lastProbeTime": null,
                        "lastTransitionTime": "2024-05-02T15:05:26Z",
                        "status": "True",
                        "type": "PodScheduled"
                    }
                ],
                "containerStatuses": [
                    {
                        "containerID": "containerd://62953833a455c0853d32a73982ed0001a2738c0523400267cba3de42a70530f5",
                        "image": "docker.io/anakli/cca:parsec_blackscholes",
                        "imageID": "docker.io/anakli/cca@sha256:7a46dab25dbb692c7c9eaa7a6bf5edeb220e3209b2460a18d05be40533849dc3",
                        "lastState": {},
                        "name": "parsec-blackscholes",
                        "ready": false,
                        "restartCount": 0,
                        "started": false,
                        "state": {
                            "terminated": {
                                "containerID": "containerd://62953833a455c0853d32a73982ed0001a2738c0523400267cba3de42a70530f5",
                                "exitCode": 0,
                                "finishedAt": "2024-05-02T15:07:22Z",
                                "reason": "Completed",
                                "startedAt": "2024-05-02T15:05:28Z"
                            }
                        }
                    }
                ],
                "hostIP": "10.0.16.2",
                "phase": "Succeeded",
                "podIP": "100.96.5.9",
                "podIPs": [
                    {
                        "ip": "100.96.5.9"
                    }
                ],
                "qosClass": "Burstable",
                "startTime": "2024-05-02T15:05:26Z"
            }
        },
        {
            "apiVersion": "v1",
            "kind": "Pod",
            "metadata": {
                "annotations": {
                    "kubernetes.io/limit-ranger": "LimitRanger plugin set: cpu request for container parsec-canneal"
                },
                "creationTimestamp": "2024-05-02T15:05:26Z",
                "generateName": "parsec-canneal-",
                "labels": {
                    "batch.kubernetes.io/controller-uid": "7595329c-b16a-4f62-8a4e-c44ee2c2ff02",
                    "batch.kubernetes.io/job-name": "parsec-canneal",
                    "controller-uid": "7595329c-b16a-4f62-8a4e-c44ee2c2ff02",
                    "job-name": "parsec-canneal"
                },
                "name": "parsec-canneal-jjkcj",
                "namespace": "default",
                "ownerReferences": [
                    {
                        "apiVersion": "batch/v1",
                        "blockOwnerDeletion": true,
                        "controller": true,
                        "kind": "Job",
                        "name": "parsec-canneal",
                        "uid": "7595329c-b16a-4f62-8a4e-c44ee2c2ff02"
                    }
                ],
                "resourceVersion": "10170",
                "uid": "a62c911d-b71a-443d-ae92-36f468c8355d"
            },
            "spec": {
                "containers": [
                    {
                        "args": [
                            "-c",
                            "taskset -c 0,1 ./run -a run -S parsec -p canneal -i native -n 2"
                        ],
                        "command": [
                            "/bin/sh"
                        ],
                        "image": "anakli/cca:parsec_canneal",
                        "imagePullPolicy": "Always",
                        "name": "parsec-canneal",
                        "resources": {
                            "requests": {
                                "cpu": "100m"
                            }
                        },
                        "terminationMessagePath": "/dev/termination-log",
                        "terminationMessagePolicy": "File",
                        "volumeMounts": [
                            {
                                "mountPath": "/var/run/secrets/kubernetes.io/serviceaccount",
                                "name": "kube-api-access-q9ssh",
                                "readOnly": true
                            }
                        ]
                    }
                ],
                "dnsPolicy": "ClusterFirst",
                "enableServiceLinks": true,
                "nodeName": "node-b-4core-dq7q",
                "nodeSelector": {
                    "cca-project-nodetype": "node-b-4core"
                },
                "preemptionPolicy": "PreemptLowerPriority",
                "priority": 0,
                "restartPolicy": "Never",
                "schedulerName": "default-scheduler",
                "securityContext": {},
                "serviceAccount": "default",
                "serviceAccountName": "default",
                "terminationGracePeriodSeconds": 30,
                "tolerations": [
                    {
                        "effect": "NoExecute",
                        "key": "node.kubernetes.io/not-ready",
                        "operator": "Exists",
                        "tolerationSeconds": 300
                    },
                    {
                        "effect": "NoExecute",
                        "key": "node.kubernetes.io/unreachable",
                        "operator": "Exists",
                        "tolerationSeconds": 300
                    }
                ],
                "volumes": [
                    {
                        "name": "kube-api-access-q9ssh",
                        "projected": {
                            "defaultMode": 420,
                            "sources": [
                                {
                                    "serviceAccountToken": {
                                        "expirationSeconds": 3607,
                                        "path": "token"
                                    }
                                },
                                {
                                    "configMap": {
                                        "items": [
                                            {
                                                "key": "ca.crt",
                                                "path": "ca.crt"
                                            }
                                        ],
                                        "name": "kube-root-ca.crt"
                                    }
                                },
                                {
                                    "downwardAPI": {
                                        "items": [
                                            {
                                                "fieldRef": {
                                                    "apiVersion": "v1",
                                                    "fieldPath": "metadata.namespace"
                                                },
                                                "path": "namespace"
                                            }
                                        ]
                                    }
                                }
                            ]
                        }
                    }
                ]
            },
            "status": {
                "conditions": [
                    {
                        "lastProbeTime": null,
                        "lastTransitionTime": "2024-05-02T15:05:26Z",
                        "reason": "PodCompleted",
                        "status": "True",
                        "type": "Initialized"
                    },
                    {
                        "lastProbeTime": null,
                        "lastTransitionTime": "2024-05-02T15:07:37Z",
                        "reason": "PodCompleted",
                        "status": "False",
                        "type": "Ready"
                    },
                    {
                        "lastProbeTime": null,
                        "lastTransitionTime": "2024-05-02T15:07:37Z",
                        "reason": "PodCompleted",
                        "status": "False",
                        "type": "ContainersReady"
                    },
                    {
                        "lastProbeTime": null,
                        "lastTransitionTime": "2024-05-02T15:05:26Z",
                        "status": "True",
                        "type": "PodScheduled"
                    }
                ],
                "containerStatuses": [
                    {
                        "containerID": "containerd://e512445d78ae3e07780e8b76fb98cf5ff16354a8abda90992d3bda23bcef66f4",
                        "image": "docker.io/anakli/cca:parsec_canneal",
                        "imageID": "docker.io/anakli/cca@sha256:cb8c3ea7a7071c7802b84179c36f52673ee099bbc2efd90149611285fec24367",
                        "lastState": {},
                        "name": "parsec-canneal",
                        "ready": false,
                        "restartCount": 0,
                        "started": false,
                        "state": {
                            "terminated": {
                                "containerID": "containerd://e512445d78ae3e07780e8b76fb98cf5ff16354a8abda90992d3bda23bcef66f4",
                                "exitCode": 0,
                                "finishedAt": "2024-05-02T15:07:35Z",
                                "reason": "Completed",
                                "startedAt": "2024-05-02T15:05:27Z"
                            }
                        }
                    }
                ],
                "hostIP": "10.0.16.5",
                "phase": "Succeeded",
                "podIP": "100.96.2.8",
                "podIPs": [
                    {
                        "ip": "100.96.2.8"
                    }
                ],
                "qosClass": "Burstable",
                "startTime": "2024-05-02T15:05:26Z"
            }
        },
        {
            "apiVersion": "v1",
            "kind": "Pod",
            "metadata": {
                "annotations": {
                    "kubernetes.io/limit-ranger": "LimitRanger plugin set: cpu request for container parsec-dedup"
                },
                "creationTimestamp": "2024-05-02T15:06:33Z",
                "generateName": "parsec-dedup-",
                "labels": {
                    "batch.kubernetes.io/controller-uid": "c05abc36-6bc5-41de-ab35-968253009dd0",
                    "batch.kubernetes.io/job-name": "parsec-dedup",
                    "controller-uid": "c05abc36-6bc5-41de-ab35-968253009dd0",
                    "job-name": "parsec-dedup"
                },
                "name": "parsec-dedup-clgfv",
                "namespace": "default",
                "ownerReferences": [
                    {
                        "apiVersion": "batch/v1",
                        "blockOwnerDeletion": true,
                        "controller": true,
                        "kind": "Job",
                        "name": "parsec-dedup",
                        "uid": "c05abc36-6bc5-41de-ab35-968253009dd0"
                    }
                ],
                "resourceVersion": "10099",
                "uid": "a9c1ce5b-1dbc-4b6c-a66c-032e90ace631"
            },
            "spec": {
                "containers": [
                    {
                        "args": [
                            "-c",
                            "taskset -c 7 ./run -a run -S parsec -p dedup -i native -n 1"
                        ],
                        "command": [
                            "/bin/sh"
                        ],
                        "image": "anakli/cca:parsec_dedup",
                        "imagePullPolicy": "Always",
                        "name": "parsec-dedup",
                        "resources": {
                            "requests": {
                                "cpu": "100m"
                            }
                        },
                        "terminationMessagePath": "/dev/termination-log",
                        "terminationMessagePolicy": "File",
                        "volumeMounts": [
                            {
                                "mountPath": "/var/run/secrets/kubernetes.io/serviceaccount",
                                "name": "kube-api-access-7626v",
                                "readOnly": true
                            }
                        ]
                    }
                ],
                "dnsPolicy": "ClusterFirst",
                "enableServiceLinks": true,
                "nodeName": "node-c-8core-v8qh",
                "nodeSelector": {
                    "cca-project-nodetype": "node-c-8core"
                },
                "preemptionPolicy": "PreemptLowerPriority",
                "priority": 0,
                "restartPolicy": "Never",
                "schedulerName": "default-scheduler",
                "securityContext": {},
                "serviceAccount": "default",
                "serviceAccountName": "default",
                "terminationGracePeriodSeconds": 30,
                "tolerations": [
                    {
                        "effect": "NoExecute",
                        "key": "node.kubernetes.io/not-ready",
                        "operator": "Exists",
                        "tolerationSeconds": 300
                    },
                    {
                        "effect": "NoExecute",
                        "key": "node.kubernetes.io/unreachable",
                        "operator": "Exists",
                        "tolerationSeconds": 300
                    }
                ],
                "volumes": [
                    {
                        "name": "kube-api-access-7626v",
                        "projected": {
                            "defaultMode": 420,
                            "sources": [
                                {
                                    "serviceAccountToken": {
                                        "expirationSeconds": 3607,
                                        "path": "token"
                                    }
                                },
                                {
                                    "configMap": {
                                        "items": [
                                            {
                                                "key": "ca.crt",
                                                "path": "ca.crt"
                                            }
                                        ],
                                        "name": "kube-root-ca.crt"
                                    }
                                },
                                {
                                    "downwardAPI": {
                                        "items": [
                                            {
                                                "fieldRef": {
                                                    "apiVersion": "v1",
                                                    "fieldPath": "metadata.namespace"
                                                },
                                                "path": "namespace"
                                            }
                                        ]
                                    }
                                }
                            ]
                        }
                    }
                ]
            },
            "status": {
                "conditions": [
                    {
                        "lastProbeTime": null,
                        "lastTransitionTime": "2024-05-02T15:06:33Z",
                        "reason": "PodCompleted",
                        "status": "True",
                        "type": "Initialized"
                    },
                    {
                        "lastProbeTime": null,
                        "lastTransitionTime": "2024-05-02T15:07:21Z",
                        "reason": "PodCompleted",
                        "status": "False",
                        "type": "Ready"
                    },
                    {
                        "lastProbeTime": null,
                        "lastTransitionTime": "2024-05-02T15:07:21Z",
                        "reason": "PodCompleted",
                        "status": "False",
                        "type": "ContainersReady"
                    },
                    {
                        "lastProbeTime": null,
                        "lastTransitionTime": "2024-05-02T15:06:33Z",
                        "status": "True",
                        "type": "PodScheduled"
                    }
                ],
                "containerStatuses": [
                    {
                        "containerID": "containerd://404b2a62dfacd57efc16c945ad4dfb8bc4279753a2d5513f16b4995929b1f772",
                        "image": "docker.io/anakli/cca:parsec_dedup",
                        "imageID": "docker.io/anakli/cca@sha256:4bd64384b51253d5f69a5bb229055c6d114e4751b19036f29d8e75d84b53164d",
                        "lastState": {},
                        "name": "parsec-dedup",
                        "ready": false,
                        "restartCount": 0,
                        "started": false,
                        "state": {
                            "terminated": {
                                "containerID": "containerd://404b2a62dfacd57efc16c945ad4dfb8bc4279753a2d5513f16b4995929b1f772",
                                "exitCode": 0,
                                "finishedAt": "2024-05-02T15:07:20Z",
                                "reason": "Completed",
                                "startedAt": "2024-05-02T15:06:35Z"
                            }
                        }
                    }
                ],
                "hostIP": "10.0.16.3",
                "phase": "Succeeded",
                "podIP": "100.96.1.19",
                "podIPs": [
                    {
                        "ip": "100.96.1.19"
                    }
                ],
                "qosClass": "Burstable",
                "startTime": "2024-05-02T15:06:33Z"
            }
        },
        {
            "apiVersion": "v1",
            "kind": "Pod",
            "metadata": {
                "annotations": {
                    "kubernetes.io/limit-ranger": "LimitRanger plugin set: cpu request for container parsec-ferret"
                },
                "creationTimestamp": "2024-05-02T15:05:26Z",
                "finalizers": [
                    "batch.kubernetes.io/job-tracking"
                ],
                "generateName": "parsec-ferret-",
                "labels": {
                    "batch.kubernetes.io/controller-uid": "bb5c2e6b-ccc5-4267-b04d-579a332267de",
                    "batch.kubernetes.io/job-name": "parsec-ferret",
                    "controller-uid": "bb5c2e6b-ccc5-4267-b04d-579a332267de",
                    "job-name": "parsec-ferret"
                },
                "name": "parsec-ferret-pn65x",
                "namespace": "default",
                "ownerReferences": [
                    {
                        "apiVersion": "batch/v1",
                        "blockOwnerDeletion": true,
                        "controller": true,
                        "kind": "Job",
                        "name": "parsec-ferret",
                        "uid": "bb5c2e6b-ccc5-4267-b04d-579a332267de"
                    }
                ],
                "resourceVersion": "10303",
                "uid": "2f82df2f-7c7d-47b1-9fac-1ff4f1f200a8"
            },
            "spec": {
                "containers": [
                    {
                        "args": [
                            "-c",
                            "taskset -c 2,3 ./run -a run -S parsec -p ferret -i native -n 2"
                        ],
                        "command": [
                            "/bin/sh"
                        ],
                        "image": "anakli/cca:parsec_ferret",
                        "imagePullPolicy": "Always",
                        "name": "parsec-ferret",
                        "resources": {
                            "requests": {
                                "cpu": "100m"
                            }
                        },
                        "terminationMessagePath": "/dev/termination-log",
                        "terminationMessagePolicy": "File",
                        "volumeMounts": [
                            {
                                "mountPath": "/var/run/secrets/kubernetes.io/serviceaccount",
                                "name": "kube-api-access-lktj9",
                                "readOnly": true
                            }
                        ]
                    }
                ],
                "dnsPolicy": "ClusterFirst",
                "enableServiceLinks": true,
                "nodeName": "node-b-4core-dq7q",
                "nodeSelector": {
                    "cca-project-nodetype": "node-b-4core"
                },
                "preemptionPolicy": "PreemptLowerPriority",
                "priority": 0,
                "restartPolicy": "Never",
                "schedulerName": "default-scheduler",
                "securityContext": {},
                "serviceAccount": "default",
                "serviceAccountName": "default",
                "terminationGracePeriodSeconds": 30,
                "tolerations": [
                    {
                        "effect": "NoExecute",
                        "key": "node.kubernetes.io/not-ready",
                        "operator": "Exists",
                        "tolerationSeconds": 300
                    },
                    {
                        "effect": "NoExecute",
                        "key": "node.kubernetes.io/unreachable",
                        "operator": "Exists",
                        "tolerationSeconds": 300
                    }
                ],
                "volumes": [
                    {
                        "name": "kube-api-access-lktj9",
                        "projected": {
                            "defaultMode": 420,
                            "sources": [
                                {
                                    "serviceAccountToken": {
                                        "expirationSeconds": 3607,
                                        "path": "token"
                                    }
                                },
                                {
                                    "configMap": {
                                        "items": [
                                            {
                                                "key": "ca.crt",
                                                "path": "ca.crt"
                                            }
                                        ],
                                        "name": "kube-root-ca.crt"
                                    }
                                },
                                {
                                    "downwardAPI": {
                                        "items": [
                                            {
                                                "fieldRef": {
                                                    "apiVersion": "v1",
                                                    "fieldPath": "metadata.namespace"
                                                },
                                                "path": "namespace"
                                            }
                                        ]
                                    }
                                }
                            ]
                        }
                    }
                ]
            },
            "status": {
                "conditions": [
                    {
                        "lastProbeTime": null,
                        "lastTransitionTime": "2024-05-02T15:05:26Z",
                        "reason": "PodCompleted",
                        "status": "True",
                        "type": "Initialized"
                    },
                    {
                        "lastProbeTime": null,
                        "lastTransitionTime": "2024-05-02T15:08:11Z",
                        "reason": "PodCompleted",
                        "status": "False",
                        "type": "Ready"
                    },
                    {
                        "lastProbeTime": null,
                        "lastTransitionTime": "2024-05-02T15:08:11Z",
                        "reason": "PodCompleted",
                        "status": "False",
                        "type": "ContainersReady"
                    },
                    {
                        "lastProbeTime": null,
                        "lastTransitionTime": "2024-05-02T15:05:26Z",
                        "status": "True",
                        "type": "PodScheduled"
                    }
                ],
                "containerStatuses": [
                    {
                        "containerID": "containerd://42ff4525a5fae50722dfe15475647f38000b9cb134b77b5c0a10e25690496de2",
                        "image": "docker.io/anakli/cca:parsec_ferret",
                        "imageID": "docker.io/anakli/cca@sha256:3f14f111258188c28b3d2b7a7f3510220f99048148a083cd9fc6168daaea9e17",
                        "lastState": {},
                        "name": "parsec-ferret",
                        "ready": false,
                        "restartCount": 0,
                        "started": false,
                        "state": {
                            "terminated": {
                                "containerID": "containerd://42ff4525a5fae50722dfe15475647f38000b9cb134b77b5c0a10e25690496de2",
                                "exitCode": 0,
                                "finishedAt": "2024-05-02T15:08:10Z",
                                "reason": "Completed",
                                "startedAt": "2024-05-02T15:05:28Z"
                            }
                        }
                    }
                ],
                "hostIP": "10.0.16.5",
                "phase": "Succeeded",
                "qosClass": "Burstable",
                "startTime": "2024-05-02T15:05:26Z"
            }
        },
        {
            "apiVersion": "v1",
            "kind": "Pod",
            "metadata": {
                "annotations": {
                    "kubernetes.io/limit-ranger": "LimitRanger plugin set: cpu request for container parsec-freqmine"
                },
                "creationTimestamp": "2024-05-02T15:05:25Z",
                "generateName": "parsec-freqmine-",
                "labels": {
                    "batch.kubernetes.io/controller-uid": "183bb3de-15e6-4826-9a92-3152c30d40f6",
                    "batch.kubernetes.io/job-name": "parsec-freqmine",
                    "controller-uid": "183bb3de-15e6-4826-9a92-3152c30d40f6",
                    "job-name": "parsec-freqmine"
                },
                "name": "parsec-freqmine-kdqm2",
                "namespace": "default",
                "ownerReferences": [
                    {
                        "apiVersion": "batch/v1",
                        "blockOwnerDeletion": true,
                        "controller": true,
                        "kind": "Job",
                        "name": "parsec-freqmine",
                        "uid": "183bb3de-15e6-4826-9a92-3152c30d40f6"
                    }
                ],
                "resourceVersion": "10242",
                "uid": "f4250409-504f-41c7-a9ec-6e295ad007c0"
            },
            "spec": {
                "containers": [
                    {
                        "args": [
                            "-c",
                            "taskset -c 0,1,2,3,4 ./run -a run -S parsec -p freqmine -i native -n 5"
                        ],
                        "command": [
                            "/bin/sh"
                        ],
                        "image": "anakli/cca:parsec_freqmine",
                        "imagePullPolicy": "Always",
                        "name": "parsec-freqmine",
                        "resources": {
                            "requests": {
                                "cpu": "100m"
                            }
                        },
                        "terminationMessagePath": "/dev/termination-log",
                        "terminationMessagePolicy": "File",
                        "volumeMounts": [
                            {
                                "mountPath": "/var/run/secrets/kubernetes.io/serviceaccount",
                                "name": "kube-api-access-6vv5k",
                                "readOnly": true
                            }
                        ]
                    }
                ],
                "dnsPolicy": "ClusterFirst",
                "enableServiceLinks": true,
                "nodeName": "node-c-8core-v8qh",
                "nodeSelector": {
                    "cca-project-nodetype": "node-c-8core"
                },
                "preemptionPolicy": "PreemptLowerPriority",
                "priority": 0,
                "restartPolicy": "Never",
                "schedulerName": "default-scheduler",
                "securityContext": {},
                "serviceAccount": "default",
                "serviceAccountName": "default",
                "terminationGracePeriodSeconds": 30,
                "tolerations": [
                    {
                        "effect": "NoExecute",
                        "key": "node.kubernetes.io/not-ready",
                        "operator": "Exists",
                        "tolerationSeconds": 300
                    },
                    {
                        "effect": "NoExecute",
                        "key": "node.kubernetes.io/unreachable",
                        "operator": "Exists",
                        "tolerationSeconds": 300
                    }
                ],
                "volumes": [
                    {
                        "name": "kube-api-access-6vv5k",
                        "projected": {
                            "defaultMode": 420,
                            "sources": [
                                {
                                    "serviceAccountToken": {
                                        "expirationSeconds": 3607,
                                        "path": "token"
                                    }
                                },
                                {
                                    "configMap": {
                                        "items": [
                                            {
                                                "key": "ca.crt",
                                                "path": "ca.crt"
                                            }
                                        ],
                                        "name": "kube-root-ca.crt"
                                    }
                                },
                                {
                                    "downwardAPI": {
                                        "items": [
                                            {
                                                "fieldRef": {
                                                    "apiVersion": "v1",
                                                    "fieldPath": "metadata.namespace"
                                                },
                                                "path": "namespace"
                                            }
                                        ]
                                    }
                                }
                            ]
                        }
                    }
                ]
            },
            "status": {
                "conditions": [
                    {
                        "lastProbeTime": null,
                        "lastTransitionTime": "2024-05-02T15:05:25Z",
                        "reason": "PodCompleted",
                        "status": "True",
                        "type": "Initialized"
                    },
                    {
                        "lastProbeTime": null,
                        "lastTransitionTime": "2024-05-02T15:07:54Z",
                        "reason": "PodCompleted",
                        "status": "False",
                        "type": "Ready"
                    },
                    {
                        "lastProbeTime": null,
                        "lastTransitionTime": "2024-05-02T15:07:54Z",
                        "reason": "PodCompleted",
                        "status": "False",
                        "type": "ContainersReady"
                    },
                    {
                        "lastProbeTime": null,
                        "lastTransitionTime": "2024-05-02T15:05:25Z",
                        "status": "True",
                        "type": "PodScheduled"
                    }
                ],
                "containerStatuses": [
                    {
                        "containerID": "containerd://a49bb2be1cca708e1624c2d8397b664f68ff3402664cc4ba54d201145afdc8c0",
                        "image": "docker.io/anakli/cca:parsec_freqmine",
                        "imageID": "docker.io/anakli/cca@sha256:c2a2f85fe345a655e84a629f04a1ca30482b9c0dd658bed193ed1d70a6395e5a",
                        "lastState": {},
                        "name": "parsec-freqmine",
                        "ready": false,
                        "restartCount": 0,
                        "started": false,
                        "state": {
                            "terminated": {
                                "containerID": "containerd://a49bb2be1cca708e1624c2d8397b664f68ff3402664cc4ba54d201145afdc8c0",
                                "exitCode": 0,
                                "finishedAt": "2024-05-02T15:07:54Z",
                                "reason": "Completed",
                                "startedAt": "2024-05-02T15:05:27Z"
                            }
                        }
                    }
                ],
                "hostIP": "10.0.16.3",
                "phase": "Succeeded",
                "podIP": "100.96.1.17",
                "podIPs": [
                    {
                        "ip": "100.96.1.17"
                    }
                ],
                "qosClass": "Burstable",
                "startTime": "2024-05-02T15:05:25Z"
            }
        },
        {
            "apiVersion": "v1",
            "kind": "Pod",
            "metadata": {
                "annotations": {
                    "kubernetes.io/limit-ranger": "LimitRanger plugin set: cpu request for container parsec-radix"
                },
                "creationTimestamp": "2024-05-02T15:05:25Z",
                "generateName": "parsec-radix-",
                "labels": {
                    "batch.kubernetes.io/controller-uid": "5af50bae-2ab6-4c47-b010-629addfbd527",
                    "batch.kubernetes.io/job-name": "parsec-radix",
                    "controller-uid": "5af50bae-2ab6-4c47-b010-629addfbd527",
                    "job-name": "parsec-radix"
                },
                "name": "parsec-radix-m78ln",
                "namespace": "default",
                "ownerReferences": [
                    {
                        "apiVersion": "batch/v1",
                        "blockOwnerDeletion": true,
                        "controller": true,
                        "kind": "Job",
                        "name": "parsec-radix",
                        "uid": "5af50bae-2ab6-4c47-b010-629addfbd527"
                    }
                ],
                "resourceVersion": "9900",
                "uid": "cc6f62ec-1b75-4e5d-aece-4853edf48cfd"
            },
            "spec": {
                "containers": [
                    {
                        "args": [
                            "-c",
                            "taskset -c 7 ./run -a run -S splash2x -p radix -i native -n 1"
                        ],
                        "command": [
                            "/bin/sh"
                        ],
                        "image": "anakli/cca:splash2x_radix",
                        "imagePullPolicy": "Always",
                        "name": "parsec-radix",
                        "resources": {
                            "requests": {
                                "cpu": "100m"
                            }
                        },
                        "terminationMessagePath": "/dev/termination-log",
                        "terminationMessagePolicy": "File",
                        "volumeMounts": [
                            {
                                "mountPath": "/var/run/secrets/kubernetes.io/serviceaccount",
                                "name": "kube-api-access-98klj",
                                "readOnly": true
                            }
                        ]
                    }
                ],
                "dnsPolicy": "ClusterFirst",
                "enableServiceLinks": true,
                "nodeName": "node-c-8core-v8qh",
                "nodeSelector": {
                    "cca-project-nodetype": "node-c-8core"
                },
                "preemptionPolicy": "PreemptLowerPriority",
                "priority": 0,
                "restartPolicy": "Never",
                "schedulerName": "default-scheduler",
                "securityContext": {},
                "serviceAccount": "default",
                "serviceAccountName": "default",
                "terminationGracePeriodSeconds": 30,
                "tolerations": [
                    {
                        "effect": "NoExecute",
                        "key": "node.kubernetes.io/not-ready",
                        "operator": "Exists",
                        "tolerationSeconds": 300
                    },
                    {
                        "effect": "NoExecute",
                        "key": "node.kubernetes.io/unreachable",
                        "operator": "Exists",
                        "tolerationSeconds": 300
                    }
                ],
                "volumes": [
                    {
                        "name": "kube-api-access-98klj",
                        "projected": {
                            "defaultMode": 420,
                            "sources": [
                                {
                                    "serviceAccountToken": {
                                        "expirationSeconds": 3607,
                                        "path": "token"
                                    }
                                },
                                {
                                    "configMap": {
                                        "items": [
                                            {
                                                "key": "ca.crt",
                                                "path": "ca.crt"
                                            }
                                        ],
                                        "name": "kube-root-ca.crt"
                                    }
                                },
                                {
                                    "downwardAPI": {
                                        "items": [
                                            {
                                                "fieldRef": {
                                                    "apiVersion": "v1",
                                                    "fieldPath": "metadata.namespace"
                                                },
                                                "path": "namespace"
                                            }
                                        ]
                                    }
                                }
                            ]
                        }
                    }
                ]
            },
            "status": {
                "conditions": [
                    {
                        "lastProbeTime": null,
                        "lastTransitionTime": "2024-05-02T15:05:25Z",
                        "reason": "PodCompleted",
                        "status": "True",
                        "type": "Initialized"
                    },
                    {
                        "lastProbeTime": null,
                        "lastTransitionTime": "2024-05-02T15:06:32Z",
                        "reason": "PodCompleted",
                        "status": "False",
                        "type": "Ready"
                    },
                    {
                        "lastProbeTime": null,
                        "lastTransitionTime": "2024-05-02T15:06:32Z",
                        "reason": "PodCompleted",
                        "status": "False",
                        "type": "ContainersReady"
                    },
                    {
                        "lastProbeTime": null,
                        "lastTransitionTime": "2024-05-02T15:05:25Z",
                        "status": "True",
                        "type": "PodScheduled"
                    }
                ],
                "containerStatuses": [
                    {
                        "containerID": "containerd://c4b68092caefe91cfdb6a58b3dd46ced4fa6f72e55685f99015fb4c97337fdc1",
                        "image": "docker.io/anakli/cca:splash2x_radix",
                        "imageID": "docker.io/anakli/cca@sha256:dbf0e10e749cf6544504ec0c90a206b8fcdc7fced6c23df536f5857f3f0ed319",
                        "lastState": {},
                        "name": "parsec-radix",
                        "ready": false,
                        "restartCount": 0,
                        "started": false,
                        "state": {
                            "terminated": {
                                "containerID": "containerd://c4b68092caefe91cfdb6a58b3dd46ced4fa6f72e55685f99015fb4c97337fdc1",
                                "exitCode": 0,
                                "finishedAt": "2024-05-02T15:06:30Z",
                                "reason": "Completed",
                                "startedAt": "2024-05-02T15:05:26Z"
                            }
                        }
                    }
                ],
                "hostIP": "10.0.16.3",
                "phase": "Succeeded",
                "podIP": "100.96.1.16",
                "podIPs": [
                    {
                        "ip": "100.96.1.16"
                    }
                ],
                "qosClass": "Burstable",
                "startTime": "2024-05-02T15:05:25Z"
            }
        },
        {
            "apiVersion": "v1",
            "kind": "Pod",
            "metadata": {
                "annotations": {
                    "kubernetes.io/limit-ranger": "LimitRanger plugin set: cpu request for container parsec-vips"
                },
                "creationTimestamp": "2024-05-02T15:05:26Z",
                "generateName": "parsec-vips-",
                "labels": {
                    "batch.kubernetes.io/controller-uid": "0ffdc787-d352-4e05-85b9-f9dffcb44ab7",
                    "batch.kubernetes.io/job-name": "parsec-vips",
                    "controller-uid": "0ffdc787-d352-4e05-85b9-f9dffcb44ab7",
                    "job-name": "parsec-vips"
                },
                "name": "parsec-vips-29vvp",
                "namespace": "default",
                "ownerReferences": [
                    {
                        "apiVersion": "batch/v1",
                        "blockOwnerDeletion": true,
                        "controller": true,
                        "kind": "Job",
                        "name": "parsec-vips",
                        "uid": "0ffdc787-d352-4e05-85b9-f9dffcb44ab7"
                    }
                ],
                "resourceVersion": "10052",
                "uid": "e5ba088e-6c45-474e-9359-80f961cec86f"
            },
            "spec": {
                "containers": [
                    {
                        "args": [
                            "-c",
                            "taskset -c 5,6 ./run -a run -S parsec -p vips -i native -n 2"
                        ],
                        "command": [
                            "/bin/sh"
                        ],
                        "image": "anakli/cca:parsec_vips",
                        "imagePullPolicy": "Always",
                        "name": "parsec-vips",
                        "resources": {
                            "requests": {
                                "cpu": "100m"
                            }
                        },
                        "terminationMessagePath": "/dev/termination-log",
                        "terminationMessagePolicy": "File",
                        "volumeMounts": [
                            {
                                "mountPath": "/var/run/secrets/kubernetes.io/serviceaccount",
                                "name": "kube-api-access-n9nsq",
                                "readOnly": true
                            }
                        ]
                    }
                ],
                "dnsPolicy": "ClusterFirst",
                "enableServiceLinks": true,
                "nodeName": "node-c-8core-v8qh",
                "nodeSelector": {
                    "cca-project-nodetype": "node-c-8core"
                },
                "preemptionPolicy": "PreemptLowerPriority",
                "priority": 0,
                "restartPolicy": "Never",
                "schedulerName": "default-scheduler",
                "securityContext": {},
                "serviceAccount": "default",
                "serviceAccountName": "default",
                "terminationGracePeriodSeconds": 30,
                "tolerations": [
                    {
                        "effect": "NoExecute",
                        "key": "node.kubernetes.io/not-ready",
                        "operator": "Exists",
                        "tolerationSeconds": 300
                    },
                    {
                        "effect": "NoExecute",
                        "key": "node.kubernetes.io/unreachable",
                        "operator": "Exists",
                        "tolerationSeconds": 300
                    }
                ],
                "volumes": [
                    {
                        "name": "kube-api-access-n9nsq",
                        "projected": {
                            "defaultMode": 420,
                            "sources": [
                                {
                                    "serviceAccountToken": {
                                        "expirationSeconds": 3607,
                                        "path": "token"
                                    }
                                },
                                {
                                    "configMap": {
                                        "items": [
                                            {
                                                "key": "ca.crt",
                                                "path": "ca.crt"
                                            }
                                        ],
                                        "name": "kube-root-ca.crt"
                                    }
                                },
                                {
                                    "downwardAPI": {
                                        "items": [
                                            {
                                                "fieldRef": {
                                                    "apiVersion": "v1",
                                                    "fieldPath": "metadata.namespace"
                                                },
                                                "path": "namespace"
                                            }
                                        ]
                                    }
                                }
                            ]
                        }
                    }
                ]
            },
            "status": {
                "conditions": [
                    {
                        "lastProbeTime": null,
                        "lastTransitionTime": "2024-05-02T15:05:26Z",
                        "reason": "PodCompleted",
                        "status": "True",
                        "type": "Initialized"
                    },
                    {
                        "lastProbeTime": null,
                        "lastTransitionTime": "2024-05-02T15:07:10Z",
                        "reason": "PodCompleted",
                        "status": "False",
                        "type": "Ready"
                    },
                    {
                        "lastProbeTime": null,
                        "lastTransitionTime": "2024-05-02T15:07:10Z",
                        "reason": "PodCompleted",
                        "status": "False",
                        "type": "ContainersReady"
                    },
                    {
                        "lastProbeTime": null,
                        "lastTransitionTime": "2024-05-02T15:05:26Z",
                        "status": "True",
                        "type": "PodScheduled"
                    }
                ],
                "containerStatuses": [
                    {
                        "containerID": "containerd://01c9ee302c736df47345059390b22bf50c7e493d551fcff88f6c52c7c4eb8838",
                        "image": "docker.io/anakli/cca:parsec_vips",
                        "imageID": "docker.io/anakli/cca@sha256:5c719838bc3d4d72143f27ca60bb5fe6f5f5b60be53b3972e73350596aa03547",
                        "lastState": {},
                        "name": "parsec-vips",
                        "ready": false,
                        "restartCount": 0,
                        "started": false,
                        "state": {
                            "terminated": {
                                "containerID": "containerd://01c9ee302c736df47345059390b22bf50c7e493d551fcff88f6c52c7c4eb8838",
                                "exitCode": 0,
                                "finishedAt": "2024-05-02T15:07:05Z",
                                "reason": "Completed",
                                "startedAt": "2024-05-02T15:05:28Z"
                            }
                        }
                    }
                ],
                "hostIP": "10.0.16.3",
                "phase": "Succeeded",
                "podIP": "100.96.1.18",
                "podIPs": [
                    {
                        "ip": "100.96.1.18"
                    }
                ],
                "qosClass": "Burstable",
                "startTime": "2024-05-02T15:05:26Z"
            }
        },
        {
            "apiVersion": "v1",
            "kind": "Pod",
            "metadata": {
                "annotations": {
                    "kubernetes.io/limit-ranger": "LimitRanger plugin set: cpu request for container memcached"
                },
                "creationTimestamp": "2024-05-02T15:04:18Z",
                "labels": {
                    "name": "some-memcached"
                },
                "name": "some-memcached",
                "namespace": "default",
                "resourceVersion": "9347",
                "uid": "45579040-f7bf-4c82-8bed-1a76cb534df3"
            },
            "spec": {
                "containers": [
                    {
                        "args": [
                            "-c",
                            "taskset -c 0 ./memcached -t 1 -u memcache"
                        ],
                        "command": [
                            "/bin/sh"
                        ],
                        "image": "anakli/memcached:t1",
                        "imagePullPolicy": "Always",
                        "name": "memcached",
                        "resources": {
                            "requests": {
                                "cpu": "100m"
                            }
                        },
                        "terminationMessagePath": "/dev/termination-log",
                        "terminationMessagePolicy": "File",
                        "volumeMounts": [
                            {
                                "mountPath": "/var/run/secrets/kubernetes.io/serviceaccount",
                                "name": "kube-api-access-7vv7b",
                                "readOnly": true
                            }
                        ]
                    }
                ],
                "dnsPolicy": "ClusterFirst",
                "enableServiceLinks": true,
                "nodeName": "node-a-2core-sljx",
                "nodeSelector": {
                    "cca-project-nodetype": "node-a-2core"
                },
                "preemptionPolicy": "PreemptLowerPriority",
                "priority": 0,
                "restartPolicy": "Always",
                "schedulerName": "default-scheduler",
                "securityContext": {},
                "serviceAccount": "default",
                "serviceAccountName": "default",
                "terminationGracePeriodSeconds": 30,
                "tolerations": [
                    {
                        "effect": "NoExecute",
                        "key": "node.kubernetes.io/not-ready",
                        "operator": "Exists",
                        "tolerationSeconds": 300
                    },
                    {
                        "effect": "NoExecute",
                        "key": "node.kubernetes.io/unreachable",
                        "operator": "Exists",
                        "tolerationSeconds": 300
                    }
                ],
                "volumes": [
                    {
                        "name": "kube-api-access-7vv7b",
                        "projected": {
                            "defaultMode": 420,
                            "sources": [
                                {
                                    "serviceAccountToken": {
                                        "expirationSeconds": 3607,
                                        "path": "token"
                                    }
                                },
                                {
                                    "configMap": {
                                        "items": [
                                            {
                                                "key": "ca.crt",
                                                "path": "ca.crt"
                                            }
                                        ],
                                        "name": "kube-root-ca.crt"
                                    }
                                },
                                {
                                    "downwardAPI": {
                                        "items": [
                                            {
                                                "fieldRef": {
                                                    "apiVersion": "v1",
                                                    "fieldPath": "metadata.namespace"
                                                },
                                                "path": "namespace"
                                            }
                                        ]
                                    }
                                }
                            ]
                        }
                    }
                ]
            },
            "status": {
                "conditions": [
                    {
                        "lastProbeTime": null,
                        "lastTransitionTime": "2024-05-02T15:04:18Z",
                        "status": "True",
                        "type": "Initialized"
                    },
                    {
                        "lastProbeTime": null,
                        "lastTransitionTime": "2024-05-02T15:04:20Z",
                        "status": "True",
                        "type": "Ready"
                    },
                    {
                        "lastProbeTime": null,
                        "lastTransitionTime": "2024-05-02T15:04:20Z",
                        "status": "True",
                        "type": "ContainersReady"
                    },
                    {
                        "lastProbeTime": null,
                        "lastTransitionTime": "2024-05-02T15:04:18Z",
                        "status": "True",
                        "type": "PodScheduled"
                    }
                ],
                "containerStatuses": [
                    {
                        "containerID": "containerd://6950b69465db1fba9a1bffb1e9402e0573960de961893d57b83ab1b2da196137",
                        "image": "docker.io/anakli/memcached:t1",
                        "imageID": "sha256:5366d8d9fe88b4f31f0f2a8e5b3a14db60afab3c6c5ee3d58be293c1fb232804",
                        "lastState": {},
                        "name": "memcached",
                        "ready": true,
                        "restartCount": 0,
                        "started": true,
                        "state": {
                            "running": {
                                "startedAt": "2024-05-02T15:04:20Z"
                            }
                        }
                    }
                ],
                "hostIP": "10.0.16.2",
                "phase": "Running",
                "podIP": "100.96.5.8",
                "podIPs": [
                    {
                        "ip": "100.96.5.8"
                    }
                ],
                "qosClass": "Burstable",
                "startTime": "2024-05-02T15:04:18Z"
            }
        }
    ],
    "kind": "List",
    "metadata": {
        "resourceVersion": ""
    }
}
